{"cameraMode":{"drawMode":0,"name":"Shaded","section":"Shading Mode"},"sceneLighting":false,"audioPlay":false,"sceneViewState":{"m_AlwaysRefresh":false,"showFog":true,"showSkybox":false,"showFlares":true,"showImageEffects":true,"showParticleSystems":true,"showVisualEffectGraphs":true,"m_FxEnabled":true},"in2DMode":false,"pivot":{"x":-0.008099215105175972,"y":0.11038788408041,"z":0.4908541440963745},"rotation":{"x":-0.5352190136909485,"y":0.2511066496372223,"z":-0.1704673320055008,"w":-0.7884078621864319},"size":0.7030799984931946,"orthographic":false}